docread/__init__.py
docread/__main__.py
docread/doc.py
docread/epub.py
docread/reader.py
docread-0.0.0.dist-info/METADATA
docread-0.0.0.dist-info/WHEEL
docread-0.0.0.dist-info/top_level.txt
docread-0.0.0.dist-info/RECORD
