Metadata-Version: 2.1
Name: docread
Version: 0.0.0
Summary: docread is a document embeddings library
Home-page: https://github.com/shellc/
Author: shellc
Author-email: shenggong.wang@gmail.com
License: MIT
Keywords: AI,Automation,LLM,RPA
Classifier: Programming Language :: Python :: 3
Requires-Python: >=3.8
Requires-Dist: EbookLib
Requires-Dist: tiktoken
Requires-Dist: python-dotenv
